odoo/addons/business_requirement/README.rst
odoo/addons/business_requirement/__init__.py
odoo/addons/business_requirement/__manifest__.py
odoo/addons/business_requirement/controllers/__init__.py
odoo/addons/business_requirement/controllers/portal.py
odoo/addons/business_requirement/data/business_data.xml
odoo/addons/business_requirement/data/business_requirement_demo.xml
odoo/addons/business_requirement/i18n/business_requirement.pot
odoo/addons/business_requirement/i18n/es.po
odoo/addons/business_requirement/i18n/fr.po
odoo/addons/business_requirement/i18n/fr_FR.po
odoo/addons/business_requirement/i18n/pt_BR.po
odoo/addons/business_requirement/i18n/sl.po
odoo/addons/business_requirement/models/__init__.py
odoo/addons/business_requirement/models/business.py
odoo/addons/business_requirement/readme/CONTRIBUTORS.rst
odoo/addons/business_requirement/readme/CREDITS.rst
odoo/addons/business_requirement/readme/DESCRIPTION.rst
odoo/addons/business_requirement/report/report.xml
odoo/addons/business_requirement/security/ir.model.access.csv
odoo/addons/business_requirement/security/security.xml
odoo/addons/business_requirement/static/description/icon.png
odoo/addons/business_requirement/static/description/icon.svg
odoo/addons/business_requirement/static/description/index.html
odoo/addons/business_requirement/static/img/br_workflow.graphml
odoo/addons/business_requirement/static/img/bus_req.png
odoo/addons/business_requirement/static/img/bus_req_alias.png
odoo/addons/business_requirement/static/img/bus_req_approved.png
odoo/addons/business_requirement/static/img/bus_req_cancel.png
odoo/addons/business_requirement/static/img/bus_req_confirmed.png
odoo/addons/business_requirement/static/img/bus_req_cust_story.png
odoo/addons/business_requirement/static/img/bus_req_done.png
odoo/addons/business_requirement/static/img/bus_req_drop.png
odoo/addons/business_requirement/static/img/bus_req_module_diag.png
odoo/addons/business_requirement/static/img/bus_req_tags.png
odoo13_addon_business_requirement-13.0.1.2.1.dist-info/METADATA
odoo13_addon_business_requirement-13.0.1.2.1.dist-info/WHEEL
odoo13_addon_business_requirement-13.0.1.2.1.dist-info/top_level.txt
odoo13_addon_business_requirement-13.0.1.2.1.dist-info/RECORD
